CHANGES.rst
MANIFEST.in
README.rst
install.sh
setup.py
doc/Makefile
doc/conf.py
doc/howto.rst
doc/index.rst
doc/install.rst
doc/make.bat
src/beast/__init__.py
src/beast/beast.py
src/ralph_beast.egg-info/PKG-INFO
src/ralph_beast.egg-info/SOURCES.txt
src/ralph_beast.egg-info/dependency_links.txt
src/ralph_beast.egg-info/entry_points.txt
src/ralph_beast.egg-info/not-zip-safe
src/ralph_beast.egg-info/requires.txt
src/ralph_beast.egg-info/top_level.txt