Metadata-Version: 1.1
Name: ralph-beast
Version: 2.1.0
Summary: Beast, ralph API client
Home-page: http://github.com/allegro/ralph_beast
Author: Grupa Allegro Sp. z o.o. and Contributors
Author-email: it-beast-dev@allegro.pl
License: Apache Software License v2.0
Platform: any
Classifier: Development Status :: 4 - Beta
Classifier: Intended Audience :: System Administrators
Classifier: License :: OSI Approved :: Apache Software License
Classifier: Natural Language :: English
Classifier: Operating System :: POSIX
Classifier: Operating System :: MacOS :: MacOS X
Classifier: Operating System :: Microsoft :: Windows :: Windows NT/2000
Classifier: Programming Language :: Python
Classifier: Programming Language :: Python :: 2.7
Classifier: Programming Language :: Python :: 2 :: Only
Classifier: Topic :: Internet :: WWW/HTTP
